{
	"backtraceGraph" : 
	{
		"commands" : 
		[
			"install"
		],
		"files" : 
		[
			"CMakeLists.txt"
		],
		"nodes" : 
		[
			{
				"file" : 0
			},
			{
				"command" : 0,
				"file" : 0,
				"line" : 69,
				"parent" : 0
			},
			{
				"command" : 0,
				"file" : 0,
				"line" : 78,
				"parent" : 0
			},
			{
				"command" : 0,
				"file" : 0,
				"line" : 83,
				"parent" : 0
			},
			{
				"command" : 0,
				"file" : 0,
				"line" : 95,
				"parent" : 0
			},
			{
				"command" : 0,
				"file" : 0,
				"line" : 106,
				"parent" : 0
			},
			{
				"command" : 0,
				"file" : 0,
				"line" : 118,
				"parent" : 0
			}
		]
	},
	"installers" : 
	[
		{
			"backtrace" : 1,
			"component" : "Unspecified",
			"destination" : "lib",
			"paths" : 
			[
				"libGDeflate.a"
			],
			"targetId" : "GDeflate::@6890427a1f51a3e7e1df",
			"targetIndex" : 0,
			"type" : "target"
		},
		{
			"backtrace" : 1,
			"component" : "Unspecified",
			"destination" : "lib",
			"paths" : 
			[
				"libGDeflate.so.1.0.0",
				"libGDeflate.so.1"
			],
			"targetId" : "GDeflate_shared::@6890427a1f51a3e7e1df",
			"targetIndex" : 1,
			"targetInstallNamelink" : "skip",
			"type" : "target"
		},
		{
			"backtrace" : 1,
			"component" : "Unspecified",
			"destination" : "lib",
			"paths" : 
			[
				"libGDeflate.so"
			],
			"targetId" : "GDeflate_shared::@6890427a1f51a3e7e1df",
			"targetIndex" : 1,
			"targetInstallNamelink" : "only",
			"type" : "target"
		},
		{
			"backtrace" : 1,
			"component" : "Unspecified",
			"destination" : "lib",
			"paths" : 
			[
				"libdeflate.a"
			],
			"targetId" : "libdeflate_static::@6890427a1f51a3e7e1df",
			"targetIndex" : 2,
			"type" : "target"
		},
		{
			"backtrace" : 1,
			"component" : "Unspecified",
			"destination" : "include/gdeflate",
			"paths" : 
			[
				"../3rdparty/libdeflate/libdeflate.h"
			],
			"type" : "file"
		},
		{
			"backtrace" : 2,
			"component" : "Unspecified",
			"destination" : "include/gdeflate",
			"paths" : 
			[
				"GDeflate.h",
				"GDeflate_c.h"
			],
			"type" : "file"
		},
		{
			"backtrace" : 3,
			"component" : "Unspecified",
			"destination" : "include/gdeflate",
			"paths" : 
			[
				"../3rdparty/libdeflate/libdeflate.h"
			],
			"type" : "file"
		},
		{
			"backtrace" : 4,
			"component" : "Unspecified",
			"destination" : "lib/cmake/GDeflate",
			"exportName" : "GDeflateTargets",
			"exportTargets" : 
			[
				{
					"id" : "GDeflate::@6890427a1f51a3e7e1df",
					"index" : 0
				},
				{
					"id" : "GDeflate_shared::@6890427a1f51a3e7e1df",
					"index" : 1
				},
				{
					"id" : "libdeflate_static::@6890427a1f51a3e7e1df",
					"index" : 2
				}
			],
			"paths" : 
			[
				"CMakeFiles/Export/0c12a5b4bcad16cfddef5ecf76f31ddd/GDeflateTargets.cmake"
			],
			"type" : "export"
		},
		{
			"backtrace" : 5,
			"component" : "Unspecified",
			"destination" : "lib/cmake/GDeflate",
			"paths" : 
			[
				"/home/toor/ripgrep/build/GDeflateConfig.cmake",
				"/home/toor/ripgrep/build/GDeflateConfigVersion.cmake"
			],
			"type" : "file"
		},
		{
			"backtrace" : 6,
			"component" : "Unspecified",
			"destination" : "lib/pkgconfig",
			"paths" : 
			[
				"/home/toor/ripgrep/build/gdeflate.pc"
			],
			"type" : "file"
		}
	],
	"paths" : 
	{
		"build" : ".",
		"source" : "."
	}
}
